LICENSE.pdf
MANIFEST.in
README.md
setup.py
OASYS1_Wavepy2.egg-info/PKG-INFO
OASYS1_Wavepy2.egg-info/SOURCES.txt
OASYS1_Wavepy2.egg-info/dependency_links.txt
OASYS1_Wavepy2.egg-info/entry_points.txt
OASYS1_Wavepy2.egg-info/namespace_packages.txt
OASYS1_Wavepy2.egg-info/not-zip-safe
OASYS1_Wavepy2.egg-info/requires.txt
OASYS1_Wavepy2.egg-info/top_level.txt
orangecontrib/__init__.py
orangecontrib/wavepy2/__init__.py
orangecontrib/wavepy2/menu/__init__.py
orangecontrib/wavepy2/menu/wavepy_menu.py
orangecontrib/wavepy2/util/__init__.py
orangecontrib/wavepy2/util/wavepy_objects.py
orangecontrib/wavepy2/util/gui/__init__.py
orangecontrib/wavepy2/util/gui/ow_crop_image.py
orangecontrib/wavepy2/util/gui/ow_crop_image_store_parameters.py
orangecontrib/wavepy2/util/gui/ow_wavepy_init_widget.py
orangecontrib/wavepy2/util/gui/ow_wavepy_interactive_widget.py
orangecontrib/wavepy2/util/gui/ow_wavepy_logger.py
orangecontrib/wavepy2/util/gui/ow_wavepy_process_widget.py
orangecontrib/wavepy2/util/gui/ow_wavepy_widget.py
orangecontrib/wavepy2/widgets/__init__.py
orangecontrib/wavepy2/widgets/diagnostic/__init__.py
orangecontrib/wavepy2/widgets/diagnostic/ow_sgz_calculate_harmonic_periods.py
orangecontrib/wavepy2/widgets/diagnostic/ow_sgz_crop_dark_image.py
orangecontrib/wavepy2/widgets/diagnostic/ow_sgz_crop_initial_image.py
orangecontrib/wavepy2/widgets/diagnostic/ow_sgz_fit_period.py
orangecontrib/wavepy2/widgets/diagnostic/ow_sgz_fit_visibility.py
orangecontrib/wavepy2/widgets/diagnostic/ow_sgz_init.py
orangecontrib/wavepy2/widgets/diagnostic/ow_sgz_logger.py
orangecontrib/wavepy2/widgets/diagnostic/ow_sgz_manager_initialization.py
orangecontrib/wavepy2/widgets/diagnostic/ow_sgz_run_calculation.py
orangecontrib/wavepy2/widgets/diagnostic/icons/sgz_calculate_harmonic_periods.png
orangecontrib/wavepy2/widgets/diagnostic/icons/sgz_crop_dark_image.png
orangecontrib/wavepy2/widgets/diagnostic/icons/sgz_crop_initial_image.png
orangecontrib/wavepy2/widgets/diagnostic/icons/sgz_fit_period.png
orangecontrib/wavepy2/widgets/diagnostic/icons/sgz_fit_visibility.png
orangecontrib/wavepy2/widgets/diagnostic/icons/sgz_init.png
orangecontrib/wavepy2/widgets/diagnostic/icons/sgz_logger.png
orangecontrib/wavepy2/widgets/diagnostic/icons/sgz_manager_initialization.png
