Metadata-Version: 2.1
Name: OASYS1-Wavepy2
Version: 0.0.23
Summary: WavePy2, data analyses of coherence and wavefront measurements at synchrotron beamlines
Home-page: https://github.com/APS-XSD-OPT-Group/OASYS1-WavePy2
Download-URL: https://github.com/APS-XSD-OPT-Group/OASYS1-WavePy2
Author: Luca Rebuffi
Author-email: lrebuffi@anl.gov
License: GPLv3
Keywords: ray-tracing,simulator,oasys1
Classifier: Development Status :: 4 - Beta
Classifier: License :: OSI Approved :: BSD License
Classifier: Natural Language :: English
Classifier: Environment :: X11 Applications :: Qt
Classifier: Environment :: Plugins
Classifier: Programming Language :: Python :: 3.7
Classifier: Topic :: Scientific/Engineering :: Visualization
Classifier: Intended Audience :: Science/Research
License-File: LICENSE.pdf
